{
  "address": "Ballaarstraat 91 bus 6, 2018 Antwerpen",
  "address_key": "BALLAARSTRAAT|91||6|2018|Antwerpen",
  "query": "\"Ballaarstraat 91\" \"2018\" \"Antwerpen\"",
  "results": [
    {
      "title": "Top 10 Best Plumbers in Redmond , WA - Angi",
      "url": "https://www.angi.com/companylist/us/wa/redmond/plumbing.htm?msockid=3c929364555a62df27c384ed54cf6387",
      "snippet": "15 apr 2026 · Read real reviews and see ratings for Redmond, WA plumbers for free! This list will help you pick the right plumbers in Redmond, WA.",
      "domain": "angi.com",
      "score": 0,
      "reasons": [],
      "emails": [],
      "socials": [],
      "kbo_numbers": []
    },
    {
      "title": "The Best 10 Plumbing near Redmond, WA 98052 - Yelp",
      "url": "https://www.yelp.com/search?cflt=plumbing&find_loc=Redmond%2C+WA+98052&msockid=3c929364555a62df27c384ed54cf6387",
      "snippet": "We called Ridgid Plumbing Service and they fixed the problem in a hurry.\" more. \"I would highly recommend Jacob to anyone in need of reliable, high-quality plumbing services.\" more. \"Best …",
      "domain": "yelp.com",
      "score": 0,
      "reasons": [],
      "emails": [],
      "socials": [],
      "kbo_numbers": []
    },
    {
      "title": "TOP 10 BEST Plumbers near Redmond , WA 98052 - Yelp",
      "url": "https://www.yelp.com/search?find_desc=plumbers&find_loc=Redmond%2C+WA+98052&msockid=3c929364555a62df27c384ed54cf6387",
      "snippet": "What are people saying about plumbing services near Redmond, WA?",
      "domain": "yelp.com",
      "score": 0,
      "reasons": [],
      "emails": [],
      "socials": [],
      "kbo_numbers": []
    },
    {
      "title": "Plumbers in Redmond, WA - The Real Yellow Pages®",
      "url": "https://www.yellowpages.com/redmond-wa/plumbers",
      "snippet": "Local Plumbers in Redmond, WA. Compare expert Plumbers, read reviews, and find contact information - THE REAL YELLOW PAGES®",
      "domain": "yellowpages.com",
      "score": 0,
      "reasons": [],
      "emails": [],
      "socials": [],
      "kbo_numbers": []
    },
    {
      "title": "Plumber Redmond WA - Puget Sound Plumbing & Heating",
      "url": "https://pugetsoundplumbing.com/service-areas/king-county/redmond/",
      "snippet": "If you need routine or emergency plumbing services, our team of expert plumbers at Puget Sound Plumbing and Heating can help. Call us today or contact us online to make an appointment or …",
      "domain": "pugetsoundplumbing.com",
      "score": 0,
      "reasons": []
    },
    {
      "title": "Top 10 Best Plumbing and heating pros in Redmond , WA | Angi",
      "url": "https://www.angi.com/companylist/us/wa/redmond/plumbing-heating-companies.htm?msockid=3c929364555a62df27c384ed54cf6387",
      "snippet": "11 nov 2025 · Read real reviews and see ratings for Redmond, WA plumbing and heating pros for free! This list will help you pick the right plumbing and heating pros in Redmond, WA.",
      "domain": "angi.com",
      "score": 0,
      "reasons": []
    },
    {
      "title": "The 10 Best Plumbing Services in Redmond, WA (with Free Estimates)",
      "url": "https://www.thumbtack.com/wa/redmond/plumbing?msockid=3c929364555a62df27c384ed54cf6387",
      "snippet": "Here is the definitive list of Redmond's plumbing services as rated by the Redmond, WA community. Want to see who made the cut?",
      "domain": "thumbtack.com",
      "score": 0,
      "reasons": []
    },
    {
      "title": "Redmond Plumber | Redmond Plumbing | Redmond Plumbers",
      "url": "https://www.beaconplumbing.net/plumbing-redmond-wa",
      "snippet": "Since 1999, Beacon Plumbing has been the trusted Redmond plumber for both residential and commercial properties. With more than 65 full-time employees and over 165,000 customers served, …",
      "domain": "beaconplumbing.net",
      "score": 0,
      "reasons": []
    }
  ],
  "status": "searched",
  "error": ""
}