{
  "address": "Bredabaan 471-473, 2170 Merksem",
  "address_key": "BREDABAAN|471|473||2170|Merksem",
  "query": "\"Bredabaan 471\" \"2170\" \"Merksem\"",
  "results": [
    {
      "title": "‫لعبة العروش - شاهدوا مسلسل بالبث أونلاين",
      "url": "https://www.justwatch.com/eg/tv-show/sr-l-rwsh",
      "snippet": "تتقاتل سبع عائلات نبيلة من أجل السيطرة على أرض - ويستيروس - الأسطورية. الاحتكاك بين العوائل يؤدي إلى حرب واسعة النطاق. في حين يستيقظ الشر القديم في أقصى الشمال. وفي خضم الحرب، نظام عسكري مهمَل - حرس الليل - هم كل ما يقف بين عالم الإنسان والأهوال الجليدية. فيديوهات: إعلانات بانر، ومقاطع …",
      "domain": "justwatch.com",
      "score": 0,
      "reasons": [],
      "emails": [],
      "socials": [],
      "kbo_numbers": []
    },
    {
      "title": "شاهد مسلسل صراع العروش - غيم أوف ثرونز اونلاين | أفلام ومسلسلات بجودة ...",
      "url": "https://osnplus.com/ar-sa/series/game-of-thrones-1185",
      "snippet": "تتلقى عائلة ستارك من وينترفيل زيارة من العائلة المالكة، بينما يشكل أمير عائلة تارغارين المنفي تحالفاً جديداً للسيطرة على العرش من جديد. هناك الكثير من الأمور التي تشغل بال التوأم لانيستر في وينترفيل. وبعد فشل إحدى المهمات، يتوجه جون وتايرون إلى الـ وول في الشمال، بينما يواجه نيد ستارك أزمة عائلية.",
      "domain": "osnplus.com",
      "score": 0,
      "reasons": [],
      "emails": [],
      "socials": [],
      "kbo_numbers": []
    },
    {
      "title": "‫لعبة العروش الموسم 1 - شاهدوا الحلقات الكاملة أونلاين",
      "url": "https://www.justwatch.com/eg/tv-show/sr-l-rwsh/season-1",
      "snippet": "‫هل يُعرض لعبة العروش الموسم 1 على Netflix أو Prime Video أو iflix إلخ؟ اعرفوا أين يمكنكم مشاهدة الحلقات الكاملة أونلاين الآن!",
      "domain": "justwatch.com",
      "score": 0,
      "reasons": [],
      "emails": [],
      "socials": [],
      "kbo_numbers": []
    },
    {
      "title": "حلقات قيم اوف ثرونز | game of thrones – Telegram",
      "url": "https://t.me/s/GOTofthrones",
      "snippet": "تريد تتابع قيم اوف ثرونز بدون تعب تحميل الحلقات وماتعرف شلون؟ جبتلك الحل 🔥. كل الي عليك تسويه تحمل تطبيق تيلي بوكس وتدخل على هذا القروب وراح تلقى فيه كل حلقات المسلسل بدون ماتحملها وتتابع براحتك. رابط القروب - https://bxlnk.com/s/zQCRa9T.",
      "domain": "t.me",
      "score": 0,
      "reasons": [],
      "emails": [],
      "socials": [],
      "kbo_numbers": []
    },
    {
      "title": "مسلسل - Game of Thrones S8 - 2019 مشاهدة اونلاين، فيديو، الإعلان، صور ...",
      "url": "https://elcinema.com/work/2051233/",
      "snippet": "في الموسم الأخير من المسلسل، تحل أخيرًا المعركة التي طال انتظارها بين (دينيريس تاريجريان)، و (جون سنو) و (سيرسي لانيستر) في سبيل بسط النفوذ الكامل على ممالك ويستروس السبعة، ومعركة ثلاثتهم مع ...",
      "domain": "elcinema.com",
      "score": 0,
      "reasons": []
    },
    {
      "title": "صراع العروش - TV Show - all complete seasons - Where to watch online ...",
      "url": "https://moviewiser.com/ae/tv/1399",
      "snippet": "لقد حُدد مصير الممالك السبع الحتمي في هذه الحلقة الأخيرة من مسلسل غيم أوف ثرونز.",
      "domain": "moviewiser.com",
      "score": 0,
      "reasons": []
    },
    {
      "title": "حلقات المسلسل : مسلسل - Game of Thrones S1 - 2011",
      "url": "https://elcinema.com/work/2010074/episodes",
      "snippet": "يشعر نيد ستارك بالحيرة ما بين واجبه تجاه الملك والعمل كساعده، وما بين البقاء بجانب عائلته، ويقابل الملك عائلة نيد، ويكتشف بران حقيقة مروعة تؤدي إلى حادث مروع. يسقط بران من قمة عالية ويدخل في غيبوبة، ويطير نيد مع أريا وسانسا إلى موطن الملك لخدمة روبرت.",
      "domain": "elcinema.com",
      "score": 0,
      "reasons": []
    },
    {
      "title": "برايم فيديو: Game of Thrones - Season 1 - Prime Video",
      "url": "https://www.primevideo.com/-/ar/detail/0JHQC04AAR1RC481KRW4S4PL4Z/",
      "snippet": "Experience the first season of this visionary HBO series based on the bestselling books by George R.R. Martin. Set in the mythical world of Westeros, 'Game of Thrones' follows the many driven inhabitants …",
      "domain": "primevideo.com",
      "score": 0,
      "reasons": []
    }
  ],
  "status": "searched",
  "error": ""
}